[
  {
    "id": "stride-hunter",
    "title": "STRIDE HUNTER",
    "description": "The Perfected Alignment Engine. Deploy a fleet of threads to hunt for factors using geometric sieving.",
    "longDescription": "Stride Hunter utilizes the 'Geometric Soul of the Sieve' to find collisions in modular space. It utilizes multi-threaded Web Workers to scan high-altitude exponents for prime factors with zero UI lag.",
    "features": [
      "Multi-core Fleet Deployment",
      "Geometric Sieve Theorem Integration",
      "Real-time Mission Progress Tracking"
    ],
    "tech": [
      "Web Workers (Parallel Processing)",
      "BigInt Precision",
      "Tailwind CSS"
    ],
    "projectPage": "./forge/projects/stride-hunter.html",
    "type": "Math",
    "version": "V13.3",
    "status": "BETA",
    "statusClass": "badge-beta",
    "buttonText": "DEPLOY",
    "image": "./assets/stride_hunter.webp",
    "action": "launchApp('./apps/stridehunterv13-3.html')"
  },
  {
    "id": "gnomonicus",
    "title": "GNOMONICUS",
    "description": "Interactive visualizer for Gnomon Volume Sums and infinite lattice arithmetic.",
    "longDescription": "An experimental arithmetic engine that visualizes the 'Gnomon' structure of integer space. It renders an infinite triangular grid where every node represents a vector slope, allowing for the real-time calculation of Volume Sums and Tape IDs using BigInt precision.",
    "features": [
      "Infinite Pan & Zoom Canvas",
      "Real-time Gnomon Summation",
      "BigInt Arithmetic Support"
    ],
    "tech": [
      "HTML5 Canvas",
      "Touch Physics",
      "Vanilla JS"
    ],
    "projectPage": "./forge/projects/gnomonicus.html",
    "type": "Math",
    "version": "V0.0.0",
    "status": "ALPHA",
    "statusClass": "badge-alpha",
    "buttonText": "EXPLORE",
    "icon": "",
    "image": "./assets/gnomonicus.jpg",
    "action": "launchApp('./apps/gnomonicus0.0.0.html')"
  },
  {
    "id": "thegeneral",
    "title": "THE GENERAL",
    "description": "Hunt factors with the SGS Poly-algo squad in real time in your browser and fast.",
    "longDescription": "A high-performance modular visualizer and factor hunting engine. Built to utilize parallel browser threads for intense number crunching without UI lag.",
    "features": ["Real-time visual lattice", "SGS Poly-algo integration", "Multi-threaded processing"],
    "tech": ["JS BigInt", "Web Workers", "Canvas API"],
    "projectPage": "./forge/projects/thegeneral0.0.34.html",
    "type": "Math",
    "version": "V0.0.34",
    "status": "ALPHA",
    "statusClass": "badge-alpha",
    "buttonText": "HUNT",
    "image": "./assets/thegeneral.jpg",
    "action": "launchApp('./apps/thegeneral0.0.34.html')"
  },
{
    "id": "gnomon-navigator",
    "title": "GNOMON NAVIGATOR",
    "description": "Visualize the 'DNA' of integers. Navigate the infinite lattice of Gnomon indexing and vector slopes.",
    "type": "Prototypes",
    "version": "V0.0.6",
    "status": "ALPHA",
    "statusClass": "badge-alpha",
    "buttonText": "NAVIGATE",
    "icon": "",
    "image": "./assets/gnomonnavigator.jpg",
    "action": "launchApp('./apps/gnomonnavigator0.0.6.html')"
  },
  {
    "id": "factor-hunter",
    "title": "FACTOR HUNTER",
    "description": "Strike composite beasts with Prime weapons.",
    "type": "Games",
    "version": "V1.2",
    "status": "LIVE",
    "statusClass": "badge-live",
    "buttonText": "HUNT",
    "icon": "👹",
    "image": "./assets/factorhunter.jpg",
    "action": "launchApp('./apps/factor-hunter.html')"
  },
  {
    "id": "residue-scanner",
    "title": "RESIDUE SCANNER",
    "description": "The Gnomon Navigator. Modular visualizer.",
    "type": "Tools",
    "version": "V0.8",
    "status": "BETA",
    "statusClass": "badge-beta",
    "buttonText": "SCAN",
    "icon": "⚗️",
    "image": "./assets/residuescanner.jpg",
    "action": "launchApp('./apps/residue-scanner.html')"
  },
  {
    "id": "pixel-alchemist",
    "title": "PIXEL ALCHEMIST",
    "description": "Transmute sprites into code arrays.",
    "type": "Tools",
    "version": "V0.1",
    "status": "TESTING",
    "statusClass": "badge-alpha",
    "buttonText": "BREW",
    "icon": "🧪",
    "action": "launchApp('./forge/entries/pixel-alchemist/index.html')"
  },
  {
    "id": "void-compass",
    "title": "VOID COMPASS",
    "description": "Procedural map generation for dungeons.",
    "type": "Prototypes",
    "version": "V0.0.1",
    "status": "ALPHA",
    "statusClass": "badge-alpha",
    "buttonText": "VIEW",
    "icon": "🧭",
    "action": "launchApp('./forge/entries/void-compass/index.html')"
  }
]
